dish/__init__.py
dish/cli.py
dish/dish.py
dish/interpreter.py
dish/parser.py
dish/procs.py
dish-0.0.0.dist-info/LICENSE
dish-0.0.0.dist-info/METADATA
dish-0.0.0.dist-info/WHEEL
dish-0.0.0.dist-info/top_level.txt
dish-0.0.0.dist-info/RECORD
