Metadata-Version: 2.1
Name: dish
Version: 0.0.0
Summary: A new, modern Unix shell implemented in pure Python with Flask-like configuration and extensibility
Home-page: https://github.com/dullbananas/dish
Author: Dull Bananas
Author-email: dull.bananas0@gmail.com
License: MIT
Platform: UNKNOWN
Classifier: Development Status :: 3 - Alpha
Classifier: Environment :: Console
Classifier: Intended Audience :: Developers
Classifier: License :: OSI Approved :: MIT License
Classifier: Natural Language :: English
Classifier: Operating System :: Unix
Classifier: Programming Language :: Python :: 3
Classifier: Programming Language :: Python :: 3.7
Classifier: Programming Language :: Python :: 3.8
Classifier: Programming Language :: Python :: 3 :: Only
Classifier: Topic :: System :: Shells
Classifier: Topic :: Utilities
Requires-Python: >=3.7
Requires-Dist: click
Requires-Dist: ansicolors
Requires-Dist: prompt-toolkit
Requires-Dist: Pygments
Requires-Dist: dulwich
